setup.py
scantask/__init__.py
scantask.egg-info/PKG-INFO
scantask.egg-info/SOURCES.txt
scantask.egg-info/dependency_links.txt
scantask.egg-info/entry_points.txt
scantask.egg-info/requires.txt
scantask.egg-info/top_level.txt