Metadata-Version: 1.0
Name: scantask
Version: 0.1
Summary: create/delete new scantask
Home-page: UNKNOWN
Author: slc
Author-email: 1427784107@qq.com
License: UNKNOWN
Platform: UNKNOWN
